{
    "cubes": [
        {
            "position": [
                1.4,
                0.0,
                0.47672838081217317
            ],
            "scale": [
                0.5,
                0.6,
                0.03
            ]
        },
        {
            "position": [
                1.4,
                -0.6,
                0.6
            ],
            "scale": [
                0.5,
                0.03,
                0.6
            ]
        },
        {
            "position": [
                1.4,
                0.0,
                0.9709618060915708
            ],
            "scale": [
                0.5,
                0.6,
                0.03
            ]
        },
        {
            "position": [
                1.4,
                0.6,
                0.6
            ],
            "scale": [
                0.5,
                0.05,
                0.6
            ]
        },
        {
            "position": [
                1.4,
                0.0,
                1.2
            ],
            "scale": [
                0.5,
                0.6,
                0.03
            ]
        }
    ],
    "cylinders": [
        {
            "position": [
                0.8787985070473877,
                -0.18329028351993548,
                0.6
            ],
            "radius": 0.030774663388584787,
            "heigth": 0.5
        },
        {
            "position": [
                0.9254370109344645,
                -0.10823072930334154,
                0.6
            ],
            "radius": 0.04131496103796571,
            "heigth": 0.5
        }
    ],
    "target": [
        [
            0.9999889309092972,
            0.004705109869154791,
            4.898476297924203e-09,
            1.1803476810455322
        ],
        [
            0.004705109869157341,
            -0.9999889309087553,
            -1.0410856205914319e-06,
            0.048273950815200806
        ],
        [
            -1.5183678429361204e-16,
            1.0410971445894412e-06,
            -0.9999999999994581,
            0.6074628829956055
        ],
        [
            0.0,
            0.0,
            0.0,
            1.0
        ]
    ],
    "robot_base": [
        [
            1.0,
            0.0,
            0.0,
            0.0
        ],
        [
            0.0,
            1.0,
            0.0,
            0.42908487084651425
        ],
        [
            0.0,
            0.0,
            1.0,
            0.0
        ],
        [
            0.0,
            0.0,
            0.0,
            1.0
        ]
    ]
}